[
  {
    "key": "6EkuFQ2bMQ",
    "imgURL": "https://i.ibb.co/GC7wdwk/v3-0047028.jpg",
    "position": "President",
    "name": "John K. Kimberlin",
    "address": "515 Crestview Manor Indianapolis, IN 46254",
    "phone": "317-297-4835",
    "email": "JohnKKimberlin@dayrep.com",
    "donations": 1000000
  },
  {
    "key": "dorXSrY0Na",
    "imgURL": "https://i.ibb.co/9y62kNw/v3-0099989.jpg",
    "position": "Deputy President Lifesaving",
    "name": "Daniel E. Simmons",
    "address": "3484 Single Street Mansfield, MA 02048",
    "phone": "781-589-6077",
    "email": "DanielESimmons@rhyta.com",
    "donations": 800000
  },
  {
    "key": "ihzSTxZ6tU",
    "imgURL": "https://i.ibb.co/pjcsYGX/v3-0131555.jpg",
    "position": "Deputy President Competition",
    "name": "David L. Williams",
    "address": "1804 Collins Street Elkland, PA 16920",
    "phone": "814-258-5240",
    "email": "DavidLWilliams@rhyta.com",
    "donations": 800000
  },
  {
    "key": "UvTAr8YeHa",
    "imgURL": "https://i.ibb.co/6gSH8Sh/v3-0170001.jpg",
    "position": "Deputy President Junior Activities and Youth",
    "name": "Patrick A. Cuevas",
    "address": "3783 Hannah Street Charlotte, NC 28217",
    "phone": "828-394-6714",
    "email": "PatrickACuevas@rhyta.com",
    "donations": 800000
  },
  {
    "key": "tNLpK9vTGA",
    "imgURL": "https://i.ibb.co/TRP6K11/v3-0336037.jpg",
    "position": "Club Captain",
    "name": "Kevin L. Casteel",
    "address": "4224 Aaron Smith Drive Harrisburg, PA 17101",
    "phone": "717-748-5122",
    "email": "KevinLCasteel@rhyta.com",
    "donations": 500000
  },
  {
    "key": "XPkjF36EoY",
    "imgURL": "https://i.ibb.co/tXRytfH/v3-0350482.jpg",
    "position": "Secretary",
    "name": "Robert L. Cullins",
    "address": "691 Murry Street Virginia Beach, VA 23462",
    "phone": "757-475-1102",
    "email": "RobertLCullins@jourrapide.com",
    "donations": 500000
  },
  {
    "key": "fpzd8tNqey",
    "imgURL": "https://i.ibb.co/fFrftZ2/v3-0392360.jpg",
    "position": "Treasurer",
    "name": "Brian M. Hill",
    "address": "735 Duffy Street Hanna, IN 46340",
    "phone": "219-797-3253",
    "email": "BrianMHill@dayrep.com",
    "donations": 500000
  },
  {
    "key": "RNQ8XV4w45",
    "imgURL": "https://i.ibb.co/pP0WrFG/v3-0409348.jpg",
    "position": "Director Education",
    "name": "Robert J. Holmes",
    "address": "1182 Platinum Drive Greensburg, PA 15601",
    "phone": "724-830-6816",
    "email": "RobertJHolmes@jourrapide.com",
    "donations": 500000
  },
  {
    "key": "Q571yy6EUI",
    "imgURL": "https://i.ibb.co/8rdDyRz/v3-0469330.jpg",
    "position": "Director Life Member",
    "name": "Joseph J. Simonsen",
    "address": "3821 Smithfield Avenue Lubbock, TX 79401",
    "phone": "806-740-5608",
    "email": "JosephJSimonsen@armyspy.com",
    "donations": 500000
  },
  {
    "key": "Dkmj3UhckN",
    "imgURL": "https://i.ibb.co/M9FSjSm/v3-0471796.jpg",
    "position": "Director Risk",
    "name": "John C. Anderson",
    "address": "2682 Chicago Avenue Fresno, CA 93721",
    "phone": "559-618-3696",
    "email": "JohnCAnderson@rhyta.com",
    "donations": 500000
  },
  {
    "key": "a4YO7DxKmH",
    "imgURL": "https://i.ibb.co/7WPVq18/v3-0705066.jpg",
    "position": "Director Water Sports",
    "name": "Doyle J. Wyatt",
    "address": "4015 White Lane Hawkinsville, GA 31036",
    "phone": "478-783-6085",
    "email": "DoyleJWyatt@dayrep.com",
    "donations": 500000
  },
  {
    "key": "627U1zxa2x",
    "imgURL": "https://i.ibb.co/vz48g2m/v3-0779161.jpg",
    "position": "Director Beach Sports",
    "name": "Jeffrey C. Carr",
    "address": "4172 Arthur Avenue Dekalb, IL 60115",
    "phone": "815-787-2917",
    "email": "JeffreyCCarr@armyspy.com",
    "donations": 500000
  },
  {
    "key": "ttQS2824xV",
    "imgURL": "https://i.ibb.co/ZV6Gtkg/v3-0791771.jpg",
    "position": "Director Special Events",
    "name": "Joseph J. Jones",
    "address": "118 Little Street Akron, OH 44319",
    "phone": "330-582-5511",
    "email": "JosephJJones@rhyta.com",
    "donations": 500000
  },
  {
    "key": "cQa8NhBUV6",
    "imgURL": "https://i.ibb.co/tX5T9Fy/v3-0998397.jpg",
    "position": "Public Officer",
    "name": "Walton S. Peterson",
    "address": "694 August Lane Shreveport, LA 71101",
    "phone": "318-393-1962",
    "email": "WaltonSPeterson@teleworm.us",
    "donations": 500000
  }
]
